imgarray/__init__.py
imgarray/saveload.py
imgarray/test_saveload.py
imgarray-1.0.dist-info/DESCRIPTION.rst
imgarray-1.0.dist-info/METADATA
imgarray-1.0.dist-info/RECORD
imgarray-1.0.dist-info/WHEEL
imgarray-1.0.dist-info/metadata.json
imgarray-1.0.dist-info/top_level.txt
