Metadata-Version: 2.0
Name: imgarray
Version: 1.0
Summary: Save and load numpy arrays as PNG images
Home-page: https://github.com/mverleg/imgarray
Author: (the author)
Author-email: mdilligaf@gmail.com
License: Revised BSD License (LICENSE.txt)
Keywords: numpy,png,pillow
Platform: UNKNOWN
Classifier: Intended Audience :: Developers
Classifier: Natural Language :: English
Classifier: License :: OSI Approved :: BSD License
Classifier: Operating System :: OS Independent
Classifier: Programming Language :: Python
Classifier: Topic :: Software Development :: Libraries :: Python Modules
Requires-Dist: numpy
Requires-Dist: pillow
